Metadata-Version: 1.0
Name: scylla-django-session-store
Version: 0.0.4
Summary: Syclla/Cassandra django session store. 
Home-page: https://github.com/mwaaas/scylla_django_session_store
Author: francismwangi
Author-email: francismwangi152@gmail.com
License: MIT
Platform: UNKNOWN
